pydev/__init__.py
pydev/__main__.py
pydev/legacy.py
pydev/messages.py
pydev/program.py
pydev/utils.py
pydev_toy-0.0.12.dist-info/METADATA
pydev_toy-0.0.12.dist-info/WHEEL
pydev_toy-0.0.12.dist-info/entry_points.txt
pydev_toy-0.0.12.dist-info/licenses/LICENSE.txt
pydev_toy-0.0.12.dist-info/RECORD
