Metadata-Version: 2.4
Name: pydev-toy
Version: 0.0.12
Summary: Command line util to manage python projects
Project-URL: homepage, https://github.com/furechan/pydev-toy
License-Expression: MIT
License-File: LICENSE.txt
Keywords: cli,pyproject
Classifier: Operating System :: OS Independent
Classifier: Programming Language :: Python :: 3
Requires-Python: >=3.10
Requires-Dist: build
Requires-Dist: click
Requires-Dist: jmespath
Requires-Dist: semver
Requires-Dist: tomli
Requires-Dist: twine
